swagger_client/__init__.py
swagger_client/api_client.py
swagger_client/configuration.py
swagger_client/rest.py
swagger_client/api/__init__.py
swagger_client/api/custom_speech_accuracy_tests_api.py
swagger_client/api/custom_speech_datasets_for_model_adaptation_api.py
swagger_client/api/custom_speech_endpoints_api.py
swagger_client/api/custom_speech_models_api.py
swagger_client/api/custom_speech_transcriptions_api.py
swagger_client/api/service_health_api.py
swagger_client/models/__init__.py
swagger_client/models/component.py
swagger_client/models/dataset.py
swagger_client/models/dataset_identity.py
swagger_client/models/dataset_update.py
swagger_client/models/endpoint.py
swagger_client/models/endpoint_data.py
swagger_client/models/endpoint_data_definition.py
swagger_client/models/endpoint_metadata_update.py
swagger_client/models/error_content.py
swagger_client/models/error_detail.py
swagger_client/models/health_status_response.py
swagger_client/models/i_read_only_dictionary2.py
swagger_client/models/i_read_only_dictionary21.py
swagger_client/models/inner_error_v2.py
swagger_client/models/model.py
swagger_client/models/model_identity.py
swagger_client/models/model_update.py
swagger_client/models/speech_endpoint_definition.py
swagger_client/models/speech_model_definition.py
swagger_client/models/test.py
swagger_client/models/test_definition.py
swagger_client/models/test_update.py
swagger_client/models/transcription.py
swagger_client/models/transcription_definition.py
swagger_client/models/transcription_update.py
swagger_client/models/web_hook_configuration.py
swagger_client/models/web_hook_update_v21.py
test/__init__.py
test/test_component.py
test/test_custom_speech_accuracy_tests_api.py
test/test_custom_speech_datasets_for_model_adaptation_api.py
test/test_custom_speech_endpoints_api.py
test/test_custom_speech_models_api.py
test/test_custom_speech_transcriptions_api.py
test/test_dataset.py
test/test_dataset_identity.py
test/test_dataset_update.py
test/test_endpoint.py
swagger_client_pivotx-1.0.0.dist-info/METADATA
swagger_client_pivotx-1.0.0.dist-info/WHEEL
swagger_client_pivotx-1.0.0.dist-info/top_level.txt
swagger_client_pivotx-1.0.0.dist-info/RECORD
